<show>
   <sequence name="scene">
      <scene>3pcntORIG.xml</scene>
   </sequence>
   <sequence name="line">
      <scene>new_filter.xml</scene>
   </sequence>
   <sequence name="grammar">
      <scene>ham_thing.xml</scene>
      <scene>hamsolilddop.xml</scene>
      <scene>2bMirror.xml</scene>
      <scene>deathspeech.xml</scene>
   </sequence>
   <sequence name="word">
      <scene>partfourone.xml</scene>
      <scene>partfourtwoA.xml</scene>
      <scene>dumb.xml</scene>
      <scene>partfourtwoB.xml</scene>
      <scene>MadOph.xml</scene>
      <scene>newgertrude.xml</scene>
      <scene>gravedigger.xml</scene>
   </sequence>
   <sequence name="letter">
      <scene>letterFive.xml</scene>
      <scene>FiveTwo.xml</scene>
   </sequence>
</show>
